ireval/__init__.py
ireval/metrics.py
README.md
ireval-0.1.1.dist-info/WHEEL
ireval-0.1.1.dist-info/METADATA
ireval-0.1.1.dist-info/RECORD
