Metadata-Version: 2.1
Name: ireval
Version: 0.1.1
Summary: 
Home-page: https://github.com/jcklie/ireval
Keywords: information retrieval,metrics,machine learning
Author: Jan-Christoph Klie 
Author-email: git@mrklie.com
Requires-Python: >=3.8,<4.0
Classifier: Development Status :: 4 - Beta
Classifier: Intended Audience :: Science/Research
Classifier: License :: OSI Approved :: Apache Software License
Classifier: Operating System :: OS Independent
Classifier: Programming Language :: Python :: 3
Classifier: Programming Language :: Python :: 3 :: Only
Classifier: Programming Language :: Python :: 3.10
Classifier: Programming Language :: Python :: 3.8
Classifier: Programming Language :: Python :: 3.9
Classifier: Topic :: Scientific/Engineering :: Artificial Intelligence
Requires-Dist: numpy (>=1.22.3,<2.0.0)
Project-URL: Repository, https://github.com/jcklie/ireval
